sga_imdb/imdb.py
sga_imdb-0.1.dist-info/METADATA
sga_imdb-0.1.dist-info/WHEEL
sga_imdb-0.1.dist-info/top_level.txt
sga_imdb-0.1.dist-info/RECORD
