Metadata-Version: 2.1
Name: sga-imdb
Version: 0.1
Summary: Extract IMDB data
Home-page: UNKNOWN
Author: AbdulkadarBabbar
Author-email: abdulkadar.babbar@sganalytics.com
License: MIT
Platform: UNKNOWN
